{
  "web": {
    "client_id": "530170943747-0d9jbv03r5gja8ii6o999fj3s6ncai5n.apps.googleusercontent.com",
    "project_id": "notification-switch",
    "auth_uri": "https://accounts.google.com/o/oauth2/auth",
    "token_uri": "https://accounts.google.com/o/oauth2/token",
    "auth_provider_x509_cert_url": "https://www.googleapis.com/oauth2/v1/certs",
    "client_secret": "OwAqLCZZL6rldt1bixY40E4Z",
    "redirect_uris": ["https://notification-switch.firebaseapp.com/__/auth/handler"],
    "javascript_origins": ["http://localhost", "http://localhost:5000", "https://notification-switch.firebaseapp.com"],
      "access_token": "ya29.GlsHBPFB_xrOvqr-krs1aU7nmiuOdUPhzaYqc172Sdj3ebkJvecfgnlEpaCVzq2VFcXMWXQcPU78xHFRYffpCCVQyoEtLMf4yGwcowaN_--Mg1QTx7H4cwIRqj73",
      "refresh_token": "1/00I_v7on53kWoClQp_g_1l9CzyEHMlopEvOb0puCRywtYHgmPQ73OPHVwXQXuClq",
      "token_type": "Bearer",
      "expiry_date": 148886192100
  }
}
